{
    "ratings": [
      {
        "quote": "I have never had so much fun playing an app!",
        "author": "Jonathan Scholl via AppStore",
        "stars": 5
      },
      {
        "quote": "Makes you hate each other in a good way haha",
        "author": "Someone else via Playstore",
        "stars": 4.5
      },
      {
        "quote": "Innovative challenges and a lot of good memories",
        "author": "Also someone else via my mind",
        "stars": 4
      },
      {
        "quote": "This is the best app ever",
        "author": "anonymous via contact form",
        "stars": 5
      },
      {
        "quote": "I would love to have powerups",
        "author": "Feedback form",
        "stars": 4.5
      },
      {
        "quote": "Give me different game modes and I would give 6/5 stars",
        "author": "Also feedback",
        "stars": 4.5
      }
    ]
  }